DenseBlock/DenseBlock.py
DenseBlock/__init__.py
denseblock-1.1.dist-info/LICENSE
denseblock-1.1.dist-info/METADATA
denseblock-1.1.dist-info/WHEEL
denseblock-1.1.dist-info/top_level.txt
denseblock-1.1.dist-info/RECORD
